{
    "metaDataVersion": "1.0.0",
    "category": "com.microchip.ide.project",
    "content": {
        "metaDataVersion": "1.3.0",
        "name": "com.microchip.mcu8.mplabx.project.avr128db48-opamp-gain-and-offset-calibration-mplab-mcc",
        "version": "2.0.1",
        "displayName": "Gain and Offset Calibration of the Analog Signal Conditioning (OPAMP) Peripheral",
        "projectName": "avr128db48-opamp-gain-and-offset-calibration-mplab-mcc",
        "shortDescription": "This MPLAB X example uses MCC Melody to show how to calibrate gain and offset on the OPAMP when configured as a Programmable Gain Amplifier (PGA). The internal DAC and ADC are used to perform the calibration procedure. No additional components needed.",
        "ide": {
            "name": "MPLAB X",
            "semverRange": ">=6.10.0"
        },
        "compiler": [
            {
                "name": "XC8",
                "semverRange": "^2.41.0"
            }
        ],
        "dfp": {
            "name": "AVR-Dx_DFP",
            "semverRange": "^2.3.272"
        },
        "configurator": {
            "name": "MCC",
            "semverRange": ">=5.0.0"
        },
        "device": {
            "metaDataVersion": "1.0.0",
            "category": "com.microchip.portal.contentRef",
            "content": {
                "metaDataVersion": "1.0.0",
                "category": "com.microchip.device",
                "name": "AVR128DB48",
                "versionRange": "*"
            }
        },
        "author": "Erling Holten Wiken",
        "peripherals": [
            "OPAMP",
            "DAC",
            "ADC",
            "VREF"
        ],
        "keywords": [
            "Operational Amplifier",
            "OPAMP",
            "Resistor Ladder",
            "Curiosity Nano",
            "Non-Inverting Amplifier",
            "PGA",
            "Gain",
            "Offset",
            "Calibration"
        ],
        "additionalData": {
            "longDescription": {
                "metaDataVersion": "1.0.0",
                "category": "com.microchip.portal.fileRef",
                "content": {
                    "metaDataVersion": "1.0.0",
                    "fileName": "./README.md",
                    "mimeType": "text/markdown"
                }
            }
        }
    }
}